{
  "extraction_time": "2025-06-07 21:40:14",
  "base_product": {
    "name": "scrigno-spa-scrigno-gold-base-1-mw115-de",
    "id": "90-29112023-054443",
    "url": "https://www.traceparts.cn/en/product/scrigno-spa-scrigno-gold-base-1-mw115-de?CatalogPath=TRACEPARTS%3ATP12002018003001&Product=90-29112023-054443"
  },
  "table_headers": [
    "Part Number",
    "Description",
    "Height (mm)",
    "Width (mm)",
    "LDB (mm)",
    "LDH (mm)"
  ],
  "total_specifications": 8,
  "specifications": [
    {
      "reference": "TBB 985 x TBH 1985 mm",
      "url": "https://www.traceparts.cn/en/product/scrigno-spa-scrigno-gold-base-1-mw115-de?CatalogPath=TRACEPARTS%3ATP12002018003001&Product=90-29112023-054443&PartNumber=TBB+985+x+TBH+1985+mm",
      "parameters": {
        "Part Number": "TBB 985 x TBH 1985 mm",
        "Description": "BASE 1FLG (TBM985X1985) 1010X2025 MW115",
        "Height (mm)": "1985",
        "Width (mm)": "985",
        "LDB (mm)": "1010",
        "LDH (mm)": "2025"
      }
    },
    {
      "reference": "TBB 735 x TBH 2235 mm",
      "url": "https://www.traceparts.cn/en/product/scrigno-spa-scrigno-gold-base-1-mw115-de?CatalogPath=TRACEPARTS%3ATP12002018003001&Product=90-29112023-054443&PartNumber=TBB+735+x+TBH+2235+mm",
      "parameters": {
        "Part Number": "TBB 735 x TBH 2235 mm",
        "Description": "BASE 1FLG (TBM735X2235) 760X2275 MW115",
        "Height (mm)": "2235",
        "Width (mm)": "735",
        "LDB (mm)": "760",
        "LDH (mm)": "2275"
      }
    },
    {
      "reference": "TBB 1110 x TBH 1985 mm",
      "url": "https://www.traceparts.cn/en/product/scrigno-spa-scrigno-gold-base-1-mw115-de?CatalogPath=TRACEPARTS%3ATP12002018003001&Product=90-29112023-054443&PartNumber=TBB+1110+x+TBH+1985+mm",
      "parameters": {
        "Part Number": "TBB 1110 x TBH 1985 mm",
        "Description": "BASE 1FLG (TBM1110X1985) 1135X2025 MW115",
        "Height (mm)": "1985",
        "Width (mm)": "1110",
        "LDB (mm)": "1135",
        "LDH (mm)": "2025"
      }
    },
    {
      "reference": "TBB 610 x TBH 2235 mm",
      "url": "https://www.traceparts.cn/en/product/scrigno-spa-scrigno-gold-base-1-mw115-de?CatalogPath=TRACEPARTS%3ATP12002018003001&Product=90-29112023-054443&PartNumber=TBB+610+x+TBH+2235+mm",
      "parameters": {
        "Part Number": "TBB 610 x TBH 2235 mm",
        "Description": "BASE 1FLG (TBM610X2235) 635X2275 MW115",
        "Height (mm)": "2235",
        "Width (mm)": "610",
        "LDB (mm)": "635",
        "LDH (mm)": "2275"
      }
    },
    {
      "reference": "TBB 1235 x TBH 2110 mm",
      "url": "https://www.traceparts.cn/en/product/scrigno-spa-scrigno-gold-base-1-mw115-de?CatalogPath=TRACEPARTS%3ATP12002018003001&Product=90-29112023-054443&PartNumber=TBB+1235+x+TBH+2110+mm",
      "parameters": {
        "Part Number": "TBB 1235 x TBH 2110 mm",
        "Description": "BASE 1FLG (TBM1235X2110) 1260X2150 MW115",
        "Height (mm)": "2110",
        "Width (mm)": "1235",
        "LDB (mm)": "1260",
        "LDH (mm)": "2150"
      }
    },
    {
      "reference": "TBB 860 x TBH 2110 mm",
      "url": "https://www.traceparts.cn/en/product/scrigno-spa-scrigno-gold-base-1-mw115-de?CatalogPath=TRACEPARTS%3ATP12002018003001&Product=90-29112023-054443&PartNumber=TBB+860+x+TBH+2110+mm",
      "parameters": {
        "Part Number": "TBB 860 x TBH 2110 mm",
        "Description": "BASE 1FLG (TBM860X2110) 885X2150 MW115",
        "Height (mm)": "2110",
        "Width (mm)": "860",
        "LDB (mm)": "885",
        "LDH (mm)": "2150"
      }
    },
    {
      "reference": "TBB 860 x TBH 2235 mm",
      "url": "https://www.traceparts.cn/en/product/scrigno-spa-scrigno-gold-base-1-mw115-de?CatalogPath=TRACEPARTS%3ATP12002018003001&Product=90-29112023-054443&PartNumber=TBB+860+x+TBH+2235+mm",
      "parameters": {
        "Part Number": "TBB 860 x TBH 2235 mm",
        "Description": "BASE 1FLG (TBM860X2235) 885X2275 MW115",
        "Height (mm)": "2235",
        "Width (mm)": "860",
        "LDB (mm)": "885",
        "LDH (mm)": "2275"
      }
    },
    {
      "reference": "TBB 985 x TBH 2235 mm",
      "url": "https://www.traceparts.cn/en/product/scrigno-spa-scrigno-gold-base-1-mw115-de?CatalogPath=TRACEPARTS%3ATP12002018003001&Product=90-29112023-054443&PartNumber=TBB+985+x+TBH+2235+mm",
      "parameters": {
        "Part Number": "TBB 985 x TBH 2235 mm",
        "Description": "BASE 1FLG (TBM985X2235) 1010X2275 MW115",
        "Height (mm)": "2235",
        "Width (mm)": "985",
        "LDB (mm)": "1010",
        "LDH (mm)": "2275"
      }
    }
  ]
}