{
  "extraction_time": "2025-06-07 21:54:17",
  "base_product": {
    "name": "smeg-professional-dishwasher-ud522d",
    "id": "90-14122022-038044",
    "url": "https://www.traceparts.cn/en/product/smeg-professional-dishwasher-ud522d?CatalogPath=TRACEPARTS%3ATP12002015002003&Product=90-14122022-038044"
  },
  "table_headers": [
    "Part Number",
    "Description",
    "Material",
    "Overall Depth (mm)",
    "Overall Height (mm)",
    "Overall Width (mm)"
  ],
  "total_specifications": 1,
  "specifications": [
    {
      "reference": "UD522D",
      "url": "https://www.traceparts.cn/en/product/smeg-professional-dishwasher-ud522d?CatalogPath=TRACEPARTS%3ATP12002015002003&Product=90-14122022-038044&PartNumber=UD522D",
      "parameters": {
        "Part Number": "UD522D",
        "Description": "Professional Dishwasher : UD522D",
        "Material": "Stainless steel AISI 304",
        "Overall Depth (mm)": "600",
        "Overall Height (mm)": "820",
        "Overall Width (mm)": "600"
      }
    }
  ]
}