{
  "extraction_time": "2025-06-07 22:08:31",
  "base_product": {
    "name": "smeg-hob-sr775ao",
    "id": "90-14122022-063757",
    "url": "https://www.traceparts.cn/en/product/smeg-hob-sr775ao?CatalogPath=TRACEPARTS%3ATP12002015002008&Product=90-14122022-063757"
  },
  "table_headers": [
    "Part Number",
    "Description",
    "Color",
    "Material",
    "Overall Depth (mm)",
    "Overall Height (mm)",
    "Overall Width (mm)"
  ],
  "total_specifications": 1,
  "specifications": [
    {
      "reference": "SR775AO",
      "url": "https://www.traceparts.cn/en/product/smeg-hob-sr775ao?CatalogPath=TRACEPARTS%3ATP12002015002008&Product=90-14122022-063757&PartNumber=SR775AO",
      "parameters": {
        "Part Number": "SR775AO",
        "Description": "Hob : SR775AO",
        "Color": "Anthracite",
        "Material": "Enamelled",
        "Overall Depth (mm)": "504",
        "Overall Height (mm)": "74",
        "Overall Width (mm)": "688"
      }
    }
  ]
}